README.md
os_exitcodes/__init__.py
os_exitcodes/enum_variant.py
os_exitcodes/int_variant.py
os_exitcodes/py.typed
os_exitcodes-1.0.1.dist-info/LICENSE
os_exitcodes-1.0.1.dist-info/WHEEL
os_exitcodes-1.0.1.dist-info/METADATA
os_exitcodes-1.0.1.dist-info/RECORD
