Metadata-Version: 2.1
Name: os-exitcodes
Version: 1.0.1
Summary: A cross-operating-system compatible library for os.EX_* constants
Home-page: https://github.com/kkirsche/os-exitcodes
Keywords: exit codes,exit,sysexit
Author: Kevin Kirsche
Author-email: kev.kirsche@gmail.com
Requires-Python: >=3.7
Classifier: Development Status :: 5 - Production/Stable
Classifier: Intended Audience :: Developers
Classifier: License :: OSI Approved :: MIT License
Classifier: Operating System :: OS Independent
Classifier: Programming Language :: Python :: 3
Classifier: Programming Language :: Python :: 3.10
Classifier: Programming Language :: Python :: 3.7
Classifier: Programming Language :: Python :: 3.8
Classifier: Programming Language :: Python :: 3.9
Classifier: Typing :: Typed
Project-URL: Repository, https://github.com/kkirsche/os-exitcodes
